parcell/__init__.py
parcell/__main__.py
parcell/connector.py
parcell/loading.py
parcell/main.py
parcell/server.py
parcell/tunnel.py
parcell/default_envs/linux.json
parcell/www/.DS_Store
parcell/www/file.html
parcell/www/index.html
parcell/www/project_select.html
parcell/www/js/.DS_Store
parcell/www/js/list.js
parcell/www/js/net.js
parcell/www/lib/.DS_Store
parcell/www/lib/font-awesome/.DS_Store
parcell/www/lib/font-awesome/HELP-US-OUT.txt
parcell/www/lib/font-awesome/css/font-awesome.css
parcell/www/lib/font-awesome/css/font-awesome.min.css
parcell/www/lib/font-awesome/fonts/FontAwesome.otf
parcell/www/lib/font-awesome/fonts/fontawesome-webfont.eot
parcell/www/lib/font-awesome/fonts/fontawesome-webfont.svg
parcell/www/lib/font-awesome/fonts/fontawesome-webfont.ttf
parcell/www/lib/font-awesome/fonts/fontawesome-webfont.woff
parcell/www/lib/font-awesome/fonts/fontawesome-webfont.woff2
parcell/www/lib/font-awesome/less/animated.less
parcell/www/lib/font-awesome/less/bordered-pulled.less
parcell/www/lib/font-awesome/less/core.less
parcell/www/lib/font-awesome/less/fixed-width.less
parcell/www/lib/font-awesome/less/font-awesome.less
parcell/www/lib/font-awesome/less/icons.less
parcell/www/lib/font-awesome/less/larger.less
parcell/www/lib/font-awesome/less/list.less
parcell/www/lib/font-awesome/less/mixins.less
parcell/www/lib/font-awesome/less/path.less
parcell/www/lib/font-awesome/less/rotated-flipped.less
parcell/www/lib/font-awesome/less/stacked.less
parcell/www/lib/font-awesome/less/variables.less
parcell/www/lib/font-awesome/scss/_animated.scss
parcell/www/lib/font-awesome/scss/_bordered-pulled.scss
parcell/www/lib/font-awesome/scss/_core.scss
parcell/www/lib/font-awesome/scss/_fixed-width.scss
parcell/www/lib/font-awesome/scss/_icons.scss
parcell/www/lib/font-awesome/scss/_larger.scss
parcell/www/lib/font-awesome/scss/_list.scss
parcell/www/lib/font-awesome/scss/_mixins.scss
parcell-0.2.3.dist-info/DESCRIPTION.rst
parcell-0.2.3.dist-info/METADATA
parcell-0.2.3.dist-info/RECORD
parcell-0.2.3.dist-info/WHEEL
parcell-0.2.3.dist-info/entry_points.txt
parcell-0.2.3.dist-info/metadata.json
parcell-0.2.3.dist-info/top_level.txt
