Metadata-Version: 2.0
Name: parcell
Version: 0.2.3
Summary: UI for local development of server executed projects.
Home-page: https://github.com/JosuaKrause/parcell/
Author: Josua Krause
Author-email: josua.krause@gmail.com
License: MIT
Keywords: parcell,remote,execution,project,management,web,UI
Platform: UNKNOWN
Classifier: Development Status :: 4 - Beta
Classifier: Intended Audience :: Information Technology
Classifier: Intended Audience :: Science/Research
Classifier: License :: OSI Approved :: MIT License
Classifier: Programming Language :: Python :: 2
Requires-Dist: pexpect
Requires-Dist: quick-cache
Requires-Dist: quick-server
Requires-Dist: tej
